<?xml version="1.0" encoding="utf-8"?><resources><string-array name="zacatecas_array"><item>Zacatecas</item><item>Jalpa</item><item>Huanusco</item><item>Villa De Cos</item><item>Miguel Azua</item><item>Sombrerete</item><item>Rio Grande</item><item>Melchor Ocampo</item><item>Loreto</item><item>Moyahua De Estrada</item><item>General Francisco R Murguia</item><item>Gral Panfilo Natera</item><item>Chalchihuites</item><item>Tepetongo</item><item>Nochistlan De Mejia</item><item>Trinidad Garcia De La Cadena</item><item>Genaro Codina</item><item>Juchipila</item><item>Luis Moya</item><item>Monte Escobedo</item><item>Santa Maria De La Paz</item><item>Morelos</item><item>Tlaltenango</item><item>Valaparaiso</item><item>Tepechitlan</item><item>Calera</item><item>Tabasco</item><item>Mezquitaldel Oro</item><item>Villa Garcia</item><item>Teul De Congalez Ortega</item><item>Moyahua</item><item>Municipio De Zacatecaz</item><item>El Plateado De Joaquin Amaro</item><item>Panuco</item><item>Teul De Gonzalez Ortega</item><item>Villa Hidalgo</item><item>Ojocaliente</item></string-array></resources>